greety.cpython-311-i386-linux-musl.so
greety-0.2.19.dist-info/top_level.txt
greety-0.2.19.dist-info/RECORD
greety-0.2.19.dist-info/METADATA
greety-0.2.19.dist-info/WHEEL
